odoo10_addon_shopinvader_product_stock_assortment-10.0.1.0.1-py3.8-nspkg.pth
odoo/addons/shopinvader_product_stock_assortment/__init__.py
odoo/addons/shopinvader_product_stock_assortment/__manifest__.py
odoo/addons/shopinvader_product_stock_assortment/models/__init__.py
odoo/addons/shopinvader_product_stock_assortment/models/shopinvader_backend.py
odoo/addons/shopinvader_product_stock_assortment/tests/__init__.py
odoo/addons/shopinvader_product_stock_assortment/tests/test_product_auto_bind.py
odoo10_addon_shopinvader_product_stock_assortment-10.0.1.0.1.dist-info/METADATA
odoo10_addon_shopinvader_product_stock_assortment-10.0.1.0.1.dist-info/WHEEL
odoo10_addon_shopinvader_product_stock_assortment-10.0.1.0.1.dist-info/namespace_packages.txt
odoo10_addon_shopinvader_product_stock_assortment-10.0.1.0.1.dist-info/top_level.txt
odoo10_addon_shopinvader_product_stock_assortment-10.0.1.0.1.dist-info/RECORD
